brokersystem/__init__.py
brokersystem/__main__.py
brokersystem/_version.py
brokersystem/agent.py
brokersystem-0.2.4.dist-info/LICENSE
brokersystem-0.2.4.dist-info/METADATA
brokersystem-0.2.4.dist-info/WHEEL
brokersystem-0.2.4.dist-info/top_level.txt
brokersystem-0.2.4.dist-info/RECORD
