Metadata-Version: 2.1
Name: brokersystem
Version: 0.2.4
Summary: A Python module for communicating with brokersystem
Author: chocolate
Classifier: Programming Language :: Python :: 3
Classifier: License :: OSI Approved :: ISC License (ISCL)
Classifier: Operating System :: OS Independent
Requires-Python: >=3.6
License-File: LICENSE
Requires-Dist: requests (>=1.0)
Requires-Dist: logzero (>=1.7)
Requires-Dist: pandas (>=1.0)
Requires-Dist: pillow (>=9.0)
